pocong/__init__.py
pocong/_version.py
pocong/cli.py
pocong/pocong.py
pocong/utils.py
pocong/media_spiders/__init__.py
pocong/proxy_spiders/__init__.py
pocong/proxy_spiders/pipelines.py
pocong/proxy_spiders/spiders/__init__.py
pocong/proxy_spiders/spiders/free_proxy_list_net_spider.py
pocong-1.1.0.dist-info/METADATA
pocong-1.1.0.dist-info/WHEEL
pocong-1.1.0.dist-info/entry_points.txt
pocong-1.1.0.dist-info/top_level.txt
pocong-1.1.0.dist-info/RECORD
